nvidia/__init__.py
nvidia/cuda_cupti/__init__.py
nvidia/cuda_cupti/include/__init__.py
nvidia/cuda_cupti/include/cuda_stdint.h
nvidia/cuda_cupti/include/cupti.h
nvidia/cuda_cupti/include/cupti_activity.h
nvidia/cuda_cupti/include/cupti_callbacks.h
nvidia/cuda_cupti/include/cupti_checkpoint.h
nvidia/cuda_cupti/include/cupti_driver_cbid.h
nvidia/cuda_cupti/include/cupti_events.h
nvidia/cuda_cupti/include/cupti_metrics.h
nvidia/cuda_cupti/include/cupti_nvtx_cbid.h
nvidia/cuda_cupti/include/cupti_pcsampling.h
nvidia/cuda_cupti/include/cupti_pcsampling_util.h
nvidia/cuda_cupti/include/cupti_profiler_target.h
nvidia/cuda_cupti/include/cupti_result.h
nvidia/cuda_cupti/include/cupti_runtime_cbid.h
nvidia/cuda_cupti/include/cupti_target.h
nvidia/cuda_cupti/include/cupti_version.h
nvidia/cuda_cupti/include/generated_cudaGL_meta.h
nvidia/cuda_cupti/include/generated_cudaVDPAU_meta.h
nvidia/cuda_cupti/include/generated_cuda_gl_interop_meta.h
nvidia/cuda_cupti/include/generated_cuda_meta.h
nvidia/cuda_cupti/include/generated_cuda_runtime_api_meta.h
nvidia/cuda_cupti/include/generated_cuda_vdpau_interop_meta.h
nvidia/cuda_cupti/include/generated_cudart_removed_meta.h
nvidia/cuda_cupti/include/generated_nvtx_meta.h
nvidia/cuda_cupti/include/nvperf_common.h
nvidia/cuda_cupti/include/nvperf_cuda_host.h
nvidia/cuda_cupti/include/nvperf_host.h
nvidia/cuda_cupti/include/nvperf_target.h
nvidia/cuda_cupti/include/Openacc/cupti_openacc.h
nvidia/cuda_cupti/include/Openmp/cupti_openmp.h
nvidia/cuda_cupti/include/Openmp/omp-tools.h
nvidia/cuda_cupti/lib/__init__.py
nvidia/cuda_cupti/lib/libcheckpoint.so
nvidia/cuda_cupti/lib/libcupti.so.11.8
nvidia/cuda_cupti/lib/libnvperf_host.so
nvidia/cuda_cupti/lib/libnvperf_target.so
nvidia/cuda_cupti/lib/libpcsamplingutil.so
nvidia_cuda_cupti_cu11-11.8.87.dist-info/License.txt
nvidia_cuda_cupti_cu11-11.8.87.dist-info/METADATA
nvidia_cuda_cupti_cu11-11.8.87.dist-info/WHEEL
nvidia_cuda_cupti_cu11-11.8.87.dist-info/top_level.txt
nvidia_cuda_cupti_cu11-11.8.87.dist-info/RECORD
